{"noPatientsTransported":"3","vhTimeNotified":"1:09:49 PM","vhTimeEnRoute":"1:09:50 PM","vhTimeAtScene":"1:09:50 PM","vhTimeCrewPatient":"1:09:50 PM","vhTimeLeftScene":"1:09:51 PM","vhTimeAtDestination":"1:09:51 PM","vhTimeAvailable":"1:09:51 PM","vhTimeBackArea":"1:09:51 PM","vhResponseToScene":"Cold","vhResponseToSceneChg":"Hot","vhResponseFromScene":"Cold","vhResponseFromSceneChg":"Hot","crwDriv":"Other","crwAtte":"EMR","crwAsst":"ACP","crwDrOth":"testgggdgdss","crwAttnOth":"","crwAsstOth":"","vhOut":"123","vhAtScn":"123","vhAtDestn":"123","vhIn":"123","vhTotal":"123"}